{"namedChunkGroups":{"polyfill":{"name":"polyfill","assets":[{"name":"webpack-runtime-282b6d4c97c1eb9acb5a.js","size":3966},{"name":"polyfill-6c526833c99df9827f20.js","size":82629}],"filteredAssets":0,"assetsSize":86595,"filteredAuxiliaryAssets":2,"auxiliaryAssetsSize":217050},"app":{"name":"app","assets":[{"name":"webpack-runtime-282b6d4c97c1eb9acb5a.js","size":3966},{"name":"framework-b257aea4e46193687338.js","size":128957},{"name":"styles.cdf5f2c9e0b47c6d8988.css","size":20971},{"name":"app-04c9a8be61e3163b0e27.js","size":67904}],"filteredAssets":0,"assetsSize":221798,"filteredAuxiliaryAssets":94,"auxiliaryAssetsSize":7086698},"component---src-pages-404-tsx":{"name":"component---src-pages-404-tsx","assets":[{"name":"commons-d0128eda968862078acf.js","size":55791},{"name":"component---src-pages-404-tsx-d533b09221062147caa4.js","size":507}],"filteredAssets":0,"assetsSize":56298,"filteredAuxiliaryAssets":2,"auxiliaryAssetsSize":190387},"component---src-pages-index-tsx":{"name":"component---src-pages-index-tsx","assets":[{"name":"commons-d0128eda968862078acf.js","size":55791},{"name":"component---src-pages-index-tsx-064a686d7f80128161a4.js","size":33994}],"filteredAssets":0,"assetsSize":89785,"filteredAuxiliaryAssets":2,"auxiliaryAssetsSize":286737},"component---src-pages-notes-tsx":{"name":"component---src-pages-notes-tsx","assets":[{"name":"commons-d0128eda968862078acf.js","size":55791},{"name":"component---src-pages-notes-tsx-87d51247821125ed89ce.js","size":2481}],"filteredAssets":0,"assetsSize":58272,"filteredAuxiliaryAssets":2,"auxiliaryAssetsSize":193918},"component---src-templates-blog-post-tsx":{"name":"component---src-templates-blog-post-tsx","assets":[{"name":"commons-d0128eda968862078acf.js","size":55791},{"name":"component---src-templates-blog-post-tsx-813846cda1d6cbaec379.js","size":2617}],"filteredAssets":0,"assetsSize":58408,"filteredAuxiliaryAssets":2,"auxiliaryAssetsSize":194661}},"assetsByChunkName":{"polyfill":["webpack-runtime-282b6d4c97c1eb9acb5a.js","polyfill-6c526833c99df9827f20.js"],"app":["webpack-runtime-282b6d4c97c1eb9acb5a.js","framework-b257aea4e46193687338.js","styles.cdf5f2c9e0b47c6d8988.css","app-04c9a8be61e3163b0e27.js"],"component---src-pages-404-tsx":["commons-d0128eda968862078acf.js","component---src-pages-404-tsx-d533b09221062147caa4.js"],"component---src-pages-index-tsx":["commons-d0128eda968862078acf.js","component---src-pages-index-tsx-064a686d7f80128161a4.js"],"component---src-pages-notes-tsx":["commons-d0128eda968862078acf.js","component---src-pages-notes-tsx-87d51247821125ed89ce.js"],"component---src-templates-blog-post-tsx":["commons-d0128eda968862078acf.js","component---src-templates-blog-post-tsx-813846cda1d6cbaec379.js"]},"childAssetsByChunkName":{}}